CHANGELOG.txt
LICENCE.txt
MANIFEST.in
README.txt
pyexer.py
setup.py
test module.py
Listoperations_AS_v0.0.1.egg-info/PKG-INFO
Listoperations_AS_v0.0.1.egg-info/SOURCES.txt
Listoperations_AS_v0.0.1.egg-info/dependency_links.txt
Listoperations_AS_v0.0.1.egg-info/top_level.txt
listoperatorAS/__init__.py