Metadata-Version: 1.1
Name: Listoperations-AS-v0.0.1
Version: 0.0.1
Summary: A very basic List Operations
Home-page: https://github.com/ashok2216-A/Pymodules-listoperations_AS
Author: Ashok kumar
Author-email: ashoksiva2216@gmail.com
License: MIT
Keywords: listoperators,sumlist,countlist,swaplist,averageoflist
Platform: UNKNOWN
Classifier: Development Status :: 5 - Production/Stable
Classifier: Intended Audience :: Education
Classifier: Operating System :: Microsoft :: Windows :: Windows 10
Classifier: License :: OSI Approved :: MIT License
Classifier: Programming Language :: Python :: 3
